django_auth_spnego/__init__.py
django_auth_spnego/backends.py
django_auth_spnego/decorators.py
django_auth_spnego/settings.py
django_auth_spnego/views.py
django_auth_spnego/templates/spnego.html
django_auth_spnego2-5.3.dist-info/LICENSE
django_auth_spnego2-5.3.dist-info/METADATA
django_auth_spnego2-5.3.dist-info/WHEEL
django_auth_spnego2-5.3.dist-info/top_level.txt
django_auth_spnego2-5.3.dist-info/RECORD
