Metadata-Version: 2.1
Name: django-auth-spnego2
Version: 5.3
Summary: Django Authentication Backend for Single Sign-On via Kerberos SPNEGO
Home-page: https://github.com/alfonsrv/django-auth-spnego
Author: Brandon Ewing, alfonsrv
Author-email: alfonsrv@protonmail.com
License: Apache 2.0
Classifier: Development Status :: 5 - Production/Stable
Classifier: Environment :: Web Environment
Classifier: Framework :: Django
Classifier: Framework :: Django :: 3.2
Classifier: Framework :: Django :: 4.2
Classifier: Framework :: Django :: 5.1
Classifier: Programming Language :: Python :: 3
Classifier: Programming Language :: Python :: 3.8
Classifier: Programming Language :: Python :: 3.9
Classifier: Programming Language :: Python :: 3.10
Classifier: Programming Language :: Python :: 3.11
Classifier: Programming Language :: Python :: 3.12
Classifier: License :: OSI Approved :: Apache Software License
Classifier: Topic :: Internet :: WWW/HTTP
Requires-Python: >=3.6
License-File: LICENSE
Requires-Dist: gssapi==1.9.0
Requires-Dist: Django>=1.11
